lastmp3/__init__.py
lastmp3/__main__.py
lastmp3/api.py
lastmp3/metadata.py
lastmp3-0.0.2.dist-info/licenses/LICENSE
lastmp3-0.0.2.dist-info/METADATA
lastmp3-0.0.2.dist-info/WHEEL
lastmp3-0.0.2.dist-info/entry_points.txt
lastmp3-0.0.2.dist-info/top_level.txt
lastmp3-0.0.2.dist-info/RECORD
