Metadata-Version: 2.4
Name: lastmp3
Version: 0.0.2
Summary: Last.fm Music Downloader - Download and tag your most recent Last.fm tracks
Author-email: Adipaadi <ajhasbeensummoned@gmail.com>
License: MIT License
Project-URL: Homepage, https://github.com/ajhasbeensummoned/lastfm_mp3_with_tags
Project-URL: Bug Tracker, https://github.com/ajhasbeensummoned/lastfm_mp3_with_tags/issues
Classifier: Programming Language :: Python :: 3
Classifier: License :: OSI Approved :: MIT License
Classifier: Operating System :: OS Independent
Requires-Python: >=3.7
License-File: LICENSE
Requires-Dist: mutagen
Requires-Dist: requests
Requires-Dist: static_ffmpeg
Requires-Dist: yt-dlp
Dynamic: license-file
